FancySchmancyTestsplit/__init__.py
FancySchmancyTestsplit/fst.py
FancySchmancyTestsplit-0.1.10.dist-info/METADATA
FancySchmancyTestsplit-0.1.10.dist-info/WHEEL
FancySchmancyTestsplit-0.1.10.dist-info/top_level.txt
FancySchmancyTestsplit-0.1.10.dist-info/RECORD
