Metadata-Version: 2.1
Name: FancySchmancyTestsplit
Version: 0.1.10
Summary: a more in-depth testsplit splitting intercategorical
Author-email: Kevin Pohl <pohl.kevin@gmail.com>
Maintainer-email: Kevin Pohl <pohl.kevin@gmail.com>
License: MIT
Keywords: test split,testsplit,train test split
Classifier: Development Status :: 3 - Alpha
Classifier: Intended Audience :: Education
Classifier: Programming Language :: Python :: 3
Requires-Python: >=3.8
Requires-Dist: numpy ==1.25.2
Requires-Dist: pandas ==2.1.3
Requires-Dist: scikit-learn ==1.3.2
